hefeng_qweather_mcp/__init__.py
hefeng_qweather_mcp/main.py
hefeng_qweather_mcp-0.4.0.dist-info/METADATA
hefeng_qweather_mcp-0.4.0.dist-info/WHEEL
hefeng_qweather_mcp-0.4.0.dist-info/entry_points.txt
hefeng_qweather_mcp-0.4.0.dist-info/top_level.txt
hefeng_qweather_mcp-0.4.0.dist-info/RECORD
