Metadata-Version: 2.4
Name: hefeng-qweather-mcp
Version: 0.4.0
Summary: 和风天气 MCP 服务 - 基于 Model Context Protocol 的天气数据查询服务
Author-email: fengyucn <your-email@example.com>
License: MIT
Project-URL: Homepage, https://github.com/fengyucn/hefeng-qweather-mcp
Project-URL: Repository, https://github.com/fengyucn/hefeng-qweather-mcp.git
Project-URL: Issues, https://github.com/fengyucn/hefeng-qweather-mcp/issues
Project-URL: Documentation, https://github.com/fengyucn/hefeng-qweather-mcp#readme
Keywords: weather,mcp,hefeng,qweather,climate
Classifier: Development Status :: 3 - Alpha
Classifier: Intended Audience :: Developers
Classifier: License :: OSI Approved :: MIT License
Classifier: Programming Language :: Python :: 3
Classifier: Programming Language :: Python :: 3.11
Classifier: Programming Language :: Python :: 3.12
Classifier: Programming Language :: Python :: 3.13
Classifier: Topic :: Scientific/Engineering :: Atmospheric Science
Classifier: Topic :: Internet :: WWW/HTTP :: Dynamic Content
Requires-Python: >=3.11
Requires-Dist: cryptography>=41.0.0
Requires-Dist: httpx>=0.25.0
Requires-Dist: mcp[cli]>=1.10.0
Requires-Dist: pyjwt>=2.8.0
Requires-Dist: python-dotenv>=1.0.0
Requires-Dist: typer>=0.12.0
